src/tt_um_controlador_microbots.v
`timescale 1ns / 1ps

module tt_um_controlador_microbots (
    input  wire [7:0] ui_in,    // Dedicated inputs
    output wire [7:0] uo_out,   // Dedicated outputs
    input  wire [7:0] uio_in,   // IOs: Input path
    output wire [7:0] uio_out,  // IOs: Output path
    output wire [7:0] uio_oe,   // IOs: Enable path (active high: 0=input, 1=output)
    input  wire       ena,      // will go high when the design is enabled
    input  wire       clk,      // clock
    input  wire       rst_n     // reset_n - low to reset
);
    wire reset;
    wire f_sensor, l_sensor, r_sensor;
    wire [4:0] data_in;
    reg motorA_d, motorA_i, motorB_d, motorB_i;
    reg [3:0] flags;
    wire [3:0] motors;

    //assign uio_oe = 8'b1111_1111; //todos output
    assign {data_in, f_sensor, l_sensor, r_sensor} = ui_in;

    reg [1:0] state, next_state;

    assign uo_out = {motors, flags[3:0]};
    assign motors[0] = motorB_i;
    assign motors[1] = motorB_d;
    assign motors[2] = motorA_i;
    assign motors[3] = motorB_d;
    assign reset = ~rst_n;

    

    parameter Standby = 2'b00;
    parameter goforward = 2'b01;
    parameter goright = 2'b10;
    parameter goleft = 2'b11;

    always @(posedge clk) begin
        if (reset)
            state <= Standby;
        else
            state <= next_state;
    end

    always @* begin
        next_state = Standby;
        case (state)
            Standby: 
                if (f_sensor == 0 && l_sensor == 0 && r_sensor == 0)
                begin
                    next_state = goforward;
                end
                else if (f_sensor == 0 && l_sensor == 1 && r_sensor == 1)
                begin
                    next_state = goforward;
                end
                else if (l_sensor == 1 && r_sensor == 0)
                begin
                    next_state = goright;
                end
                else if (f_sensor == 1 && r_sensor == 0)
                begin
                    next_state = goright;
                end
                else if (l_sensor == 0 && r_sensor == 1)
                begin
                    next_state = goleft;
                end
            goforward: 
                if (f_sensor == 0 && l_sensor == 0 && r_sensor == 0)
                begin
                    next_state = state;
                end
                else if (f_sensor == 0 && l_sensor == 1 && r_sensor == 1)
                begin
                    next_state = state;
                end
            goright: 
                if (l_sensor == 1 && r_sensor == 0)
                begin
                    next_state = state;
                end
            goleft: 
                if (l_sensor == 0 && r_sensor == 1)
                begin
                    next_state = state;
                end
        endcase
    end

    always @* begin //se definen las polarizaciones de los motores 
        case (state)
            Standby : begin
                motorB_i = 0;
                motorB_d = 0;
                motorA_i = 0;
                motorA_d = 0;
            end
            goforward: begin
                motorB_i = 0;
                motorB_d = 1;
                motorA_i = 0;
                motorA_d = 1;
            end
            goright: begin
                motorB_i = 1;
                motorB_d = 0;
                motorA_i = 0;
                motorA_d = 1;
            end
            goleft: begin
                motorB_i = 0;
                motorB_d = 1;
                motorA_i = 1;
                motorA_d = 0;
            end
        endcase
    end
endmodule

src/tb_tt_um_controlador_microbots.v
module tb_tt_um_controlador_microbots;

  reg clk;
  reg rst_n;
  reg [7:0] ui_in;
  
  wire [7:0] uo_out;
  wire [7:0] uio_in;
  wire [7:0] uio_out;
  wire [7:0] uio_oe;
  wire ena;

  tt_um_controlador_microbots dut (
    .ui_in(ui_in),
    .uo_out(uo_out),
    .uio_in(uio_in),
    .uio_out(uio_out),
    .uio_oe(uio_oe),
    .ena(ena),
    .clk(clk),
    .rst_n(rst_n)
  );

  initial begin
    $dumpfile("tb_tt_um_controlador_microbots.vcd");
    $dumpvars(0, tb_tt_um_controlador_microbots);

    clk = 0;
    forever #5 clk = ~clk;
  end

  initial begin
    rst_n = 0;
    ui_in = 8'b00000000;
    #10 rst_n = 1;
    
    // Wait a few cycles for initialization
    #20;

    // Run the test
    repeat (10) begin
      ui_in = 8'b00000001;  
      #20;
      ui_in = 8'b00000010; 
      #20;
      ui_in = 8'b00000011;
      #20;
      ui_in = 8'b00000100; 
      #20;
      ui_in = 8'b00000101;  
      #20;
      ui_in = 8'b00000110;  
      #20;
      ui_in = 8'b00000111;  
      #20;
      ui_in = 8'b00000000;  // No sensors active
      #0;
    end
    
    $finish;
  end

endmodule

src/tb_tt_um_controlador_microbots.vcd
$date
	Wed Aug 23 04:06:38 2023
$end
$version
	Icarus Verilog
$end
$timescale
	1ps
$end
$scope module tb_tt_um_controlador_microbots $end
$var wire 1 ! ena $end
$var wire 8 " uio_in [7:0] $end
$var wire 8 # uio_oe [7:0] $end
$var wire 8 $ uio_out [7:0] $end
$var wire 8 % uo_out [7:0] $end
$var reg 1 & clk $end
$var reg 1 ' rst_n $end
$var reg 8 ( ui_in [7:0] $end
$scope module dut $end
$var wire 1 & clk $end
$var wire 1 ! ena $end
$var wire 1 ) reset $end
$var wire 1 ' rst_n $end
$var wire 8 * ui_in [7:0] $end
$var wire 8 + uio_in [7:0] $end
$var wire 8 , uio_oe [7:0] $end
$var wire 8 - uio_out [7:0] $end
$var wire 8 . uo_out [7:0] $end
$var wire 1 / r_sensor $end
$var wire 4 0 motors [3:0] $end
$var wire 1 1 l_sensor $end
$var wire 1 2 f_sensor $end
$var wire 5 3 data_in [4:0] $end
$var parameter 2 4 Standby $end
$var parameter 2 5 goforward $end
$var parameter 2 6 goleft $end
$var parameter 2 7 goright $end
$var reg 4 8 flags [3:0] $end
$var reg 1 9 motorA_d $end
$var reg 1 : motorA_i $end
$var reg 1 ; motorB_d $end
$var reg 1 < motorB_i $end
$var reg 2 = next_state [1:0] $end
$var reg 2 > state [1:0] $end
$upscope $end
$upscope $end
$enddefinitions $end
$comment Show the parameter values. $end
$dumpall
b10 7
b11 6
b1 5
b0 4
$end
#0
$dumpvars
bx >
b0 =
x<
x;
x:
x9
bx 8
b0 3
02
01
bx 0
0/
bx .
bz -
bz ,
bz +
b0 *
1)
b0 (
0'
0&
bx %
bz $
bz #
bz "
z!
$end
#5000
09
0:
0;
b0xxxx %
b0xxxx .
b0 0
0<
b1 =
b0 >
1&
#10000
0)
0&
1'
#15000
19
b1010xxxx %
b1010xxxx .
b1010 0
1;
b1 =
b1 >
1&
#20000
0&
#25000
1&
#30000
b0 =
1/
0&
b1 (
b1 *
#35000
09
b0xxxx %
b0xxxx .
b0 0
0;
b11 =
b0 >
1&
#40000
0&
#45000
1:
b1110xxxx %
b1110xxxx .
b1110 0
1;
b11 =
b11 >
1&
#50000
b0 =
11
0/
0&
b10 (
b10 *
#55000
0:
b0xxxx %
b0xxxx .
b0 0
0;
b10 =
b0 >
1&
#60000
0&
#65000
19
b1xxxx %
b1xxxx .
b1 0
1<
b10 =
b10 >
1&
#70000
b0 =
1/
0&
b11 (
b11 *
#75000
09
b0xxxx %
b0xxxx .
b0 0
0<
b1 =
b0 >
1&
#80000
0&
#85000
19
b1010xxxx %
b1010xxxx .
b1010 0
1;
b1 =
b1 >
1&
#90000
b0 =
12
01
0/
0&
b100 (
b100 *
#95000
09
b0xxxx %
b0xxxx .
b0 0
0;
b10 =
b0 >
1&
#100000
0&
#105000
19
b1xxxx %
b1xxxx .
b1 0
1<
b0 =
b10 >
1&
#110000
1/
0&
b101 (
b101 *
#115000
09
b0xxxx %
b0xxxx .
b0 0
0<
b11 =
b0 >
1&
#120000
0&
#125000
1:
b1110xxxx %
b1110xxxx .
b1110 0
1;
b11 =
b11 >
1&
#130000
b0 =
11
0/
0&
b110 (
b110 *
#135000
0:
b0xxxx %
b0xxxx .
b0 0
0;
b10 =
b0 >
1&
#140000
0&
#145000
19
b1xxxx %
b1xxxx .
b1 0
1<
b10 =
b10 >
1&
#150000
b0 =
1/
0&
b111 (
b111 *
#155000
09
b0xxxx %
b0xxxx .
b0 0
0<
b0 >
1&
#160000
0&
#165000
1&
#170000
b11 =
02
01
1/
0&
b1 (
b1 *
#175000
1:
b1110xxxx %
b1110xxxx .
b1110 0
1;
b11 =
b11 >
1&
#180000
0&
#185000
1&
#190000
b0 =
11
0/
0&
b10 (
b10 *
#195000
0:
b0xxxx %
b0xxxx .
b0 0
0;
b10 =
b0 >
1&
#200000
0&
#205000
19
b1xxxx %
b1xxxx .
b1 0
1<
b10 =
b10 >
1&
#210000
b0 =
1/
0&
b11 (
b11 *
#215000
09
b0xxxx %
b0xxxx .
b0 0
0<
b1 =
b0 >
1&
#220000
0&
#225000
19
b1010xxxx %
b1010xxxx .
b1010 0
1;
b1 =
b1 >
1&
#230000
b0 =
12
01
0/
0&
b100 (
b100 *
#235000
09
b0xxxx %
b0xxxx .
b0 0
0;
b10 =
b0 >
1&
#240000
0&
#245000
19
b1xxxx %
b1xxxx .
b1 0
1<
b0 =
b10 >
1&
#250000
1/
0&
b101 (
b101 *
#255000
09
b0xxxx %
b0xxxx .
b0 0
0<
b11 =
b0 >
1&
#260000
0&
#265000
1:
b1110xxxx %
b1110xxxx .
b1110 0
1;
b11 =
b11 >
1&
#270000
b0 =
11
0/
0&
b110 (
b110 *
#275000
0:
b0xxxx %
b0xxxx .
b0 0
0;
b10 =
b0 >
1&
#280000
0&
#285000
19
b1xxxx %
b1xxxx .
b1 0
1<
b10 =
b10 >
1&
#290000
b0 =
1/
0&
b111 (
b111 *
#295000
09
b0xxxx %
b0xxxx .
b0 0
0<
b0 >
1&
#300000
0&
#305000
1&
#310000
b11 =
02
01
1/
0&
b1 (
b1 *
#315000
1:
b1110xxxx %
b1110xxxx .
b1110 0
1;
b11 =
b11 >
1&
#320000
0&
#325000
1&
#330000
b0 =
11
0/
0&
b10 (
b10 *
#335000
0:
b0xxxx %
b0xxxx .
b0 0
0;
b10 =
b0 >
1&
#340000
0&
#345000
19
b1xxxx %
b1xxxx .
b1 0
1<
b10 =
b10 >
1&
#350000
b0 =
1/
0&
b11 (
b11 *
#355000
09
b0xxxx %
b0xxxx .
b0 0
0<
b1 =
b0 >
1&
#360000
0&
#365000
19
b1010xxxx %
b1010xxxx .
b1010 0
1;
b1 =
b1 >
1&
#370000
b0 =
12
01
0/
0&
b100 (
b100 *
#375000
09
b0xxxx %
b0xxxx .
b0 0
0;
b10 =
b0 >
1&
#380000
0&
#385000
19
b1xxxx %
b1xxxx .
b1 0
1<
b0 =
b10 >
1&
#390000
1/
0&
b101 (
b101 *
#395000
09
b0xxxx %
b0xxxx .
b0 0
0<
b11 =
b0 >
1&
#400000
0&
#405000
1:
b1110xxxx %
b1110xxxx .
b1110 0
1;
b11 =
b11 >
1&
#410000
b0 =
11
0/
0&
b110 (
b110 *
#415000
0:
b0xxxx %
b0xxxx .
b0 0
0;
b10 =
b0 >
1&
#420000
0&
#425000
19
b1xxxx %
b1xxxx .
b1 0
1<
b10 =
b10 >
1&
#430000
b0 =
1/
0&
b111 (
b111 *
#435000
09
b0xxxx %
b0xxxx .
b0 0
0<
b0 >
1&
#440000
0&
#445000
1&
#450000
b11 =
02
01
1/
0&
b1 (
b1 *
#455000
1:
b1110xxxx %
b1110xxxx .
b1110 0
1;
b11 =
b11 >
1&
#460000
0&
#465000
1&
#470000
b0 =
11
0/
0&
b10 (
b10 *
#475000
0:
b0xxxx %
b0xxxx .
b0 0
0;
b10 =
b0 >
1&
#480000
0&
#485000
19
b1xxxx %
b1xxxx .
b1 0
1<
b10 =
b10 >
1&
#490000
b0 =
1/
0&
b11 (
b11 *
#495000
09
b0xxxx %
b0xxxx .
b0 0
0<
b1 =
b0 >
1&
#500000
0&
#505000
19
b1010xxxx %
b1010xxxx .
b1010 0
1;
b1 =
b1 >
1&
#510000
b0 =
12
01
0/
0&
b100 (
b100 *
#515000
09
b0xxxx %
b0xxxx .
b0 0
0;
b10 =
b0 >
1&
#520000
0&
#525000
19
b1xxxx %
b1xxxx .
b1 0
1<
b0 =
b10 >
1&
#530000
1/
0&
b101 (
b101 *
#535000
09
b0xxxx %
b0xxxx .
b0 0
0<
b11 =
b0 >
1&
#540000
0&
#545000
1:
b1110xxxx %
b1110xxxx .
b1110 0
1;
b11 =
b11 >
1&
#550000
b0 =
11
0/
0&
b110 (
b110 *
#555000
0:
b0xxxx %
b0xxxx .
b0 0
0;
b10 =
b0 >
1&
#560000
0&
#565000
19
b1xxxx %
b1xxxx .
b1 0
1<
b10 =
b10 >
1&
#570000
b0 =
1/
0&
b111 (
b111 *
#575000
09
b0xxxx %
b0xxxx .
b0 0
0<
b0 >
1&
#580000
0&
#585000
1&
#590000
b11 =
02
01
1/
0&
b1 (
b1 *
#595000
1:
b1110xxxx %
b1110xxxx .
b1110 0
1;
b11 =
b11 >
1&
#600000
0&
#605000
1&
#610000
b0 =
11
0/
0&
b10 (
b10 *
#615000
0:
b0xxxx %
b0xxxx .
b0 0
0;
b10 =
b0 >
1&
#620000
0&
#625000
19
b1xxxx %
b1xxxx .
b1 0
1<
b10 =
b10 >
1&
#630000
b0 =
1/
0&
b11 (
b11 *
#635000
09
b0xxxx %
b0xxxx .
b0 0
0<
b1 =
b0 >
1&
#640000
0&
#645000
19
b1010xxxx %
b1010xxxx .
b1010 0
1;
b1 =
b1 >
1&
#650000
b0 =
12
01
0/
0&
b100 (
b100 *
#655000
09
b0xxxx %
b0xxxx .
b0 0
0;
b10 =
b0 >
1&
#660000
0&
#665000
19
b1xxxx %
b1xxxx .
b1 0
1<
b0 =
b10 >
1&
#670000
1/
0&
b101 (
b101 *
#675000
09
b0xxxx %
b0xxxx .
b0 0
0<
b11 =
b0 >
1&
#680000
0&
#685000
1:
b1110xxxx %
b1110xxxx .
b1110 0
1;
b11 =
b11 >
1&
#690000
b0 =
11
0/
0&
b110 (
b110 *
#695000
0:
b0xxxx %
b0xxxx .
b0 0
0;
b10 =
b0 >
1&
#700000
0&
#705000
19
b1xxxx %
b1xxxx .
b1 0
1<
b10 =
b10 >
1&
#710000
b0 =
1/
0&
b111 (
b111 *
#715000
09
b0xxxx %
b0xxxx .
b0 0
0<
b0 >
1&
#720000
0&
#725000
1&
#730000
b11 =
02
01
1/
0&
b1 (
b1 *
#735000
1:
b1110xxxx %
b1110xxxx .
b1110 0
1;
b11 =
b11 >
1&
#740000
0&
#745000
1&
#750000
b0 =
11
0/
0&
b10 (
b10 *
#755000
0:
b0xxxx %
b0xxxx .
b0 0
0;
b10 =
b0 >
1&
#760000
0&
#765000
19
b1xxxx %
b1xxxx .
b1 0
1<
b10 =
b10 >
1&
#770000
b0 =
1/
0&
b11 (
b11 *
#775000
09
b0xxxx %
b0xxxx .
b0 0
0<
b1 =
b0 >
1&
#780000
0&
#785000
19
b1010xxxx %
b1010xxxx .
b1010 0
1;
b1 =
b1 >
1&
#790000
b0 =
12
01
0/
0&
b100 (
b100 *
#795000
09
b0xxxx %
b0xxxx .
b0 0
0;
b10 =
b0 >
1&
#800000
0&
#805000
19
b1xxxx %
b1xxxx .
b1 0
1<
b0 =
b10 >
1&
#810000
1/
0&
b101 (
b101 *
#815000
09
b0xxxx %
b0xxxx .
b0 0
0<
b11 =
b0 >
1&
#820000
0&
#825000
1:
b1110xxxx %
b1110xxxx .
b1110 0
1;
b11 =
b11 >
1&
#830000
b0 =
11
0/
0&
b110 (
b110 *
#835000
0:
b0xxxx %
b0xxxx .
b0 0
0;
b10 =
b0 >
1&
#840000
0&
#845000
19
b1xxxx %
b1xxxx .
b1 0
1<
b10 =
b10 >
1&
#850000
b0 =
1/
0&
b111 (
b111 *
#855000
09
b0xxxx %
b0xxxx .
b0 0
0<
b0 >
1&
#860000
0&
#865000
1&
#870000
b11 =
02
01
1/
0&
b1 (
b1 *
#875000
1:
b1110xxxx %
b1110xxxx .
b1110 0
1;
b11 =
b11 >
1&
#880000
0&
#885000
1&
#890000
b0 =
11
0/
0&
b10 (
b10 *
#895000
0:
b0xxxx %
b0xxxx .
b0 0
0;
b10 =
b0 >
1&
#900000
0&
#905000
19
b1xxxx %
b1xxxx .
b1 0
1<
b10 =
b10 >
1&
#910000
b0 =
1/
0&
b11 (
b11 *
#915000
09
b0xxxx %
b0xxxx .
b0 0
0<
b1 =
b0 >
1&
#920000
0&
#925000
19
b1010xxxx %
b1010xxxx .
b1010 0
1;
b1 =
b1 >
1&
#930000
b0 =
12
01
0/
0&
b100 (
b100 *
#935000
09
b0xxxx %
b0xxxx .
b0 0
0;
b10 =
b0 >
1&
#940000
0&
#945000
19
b1xxxx %
b1xxxx .
b1 0
1<
b0 =
b10 >
1&
#950000
1/
0&
b101 (
b101 *
#955000
09
b0xxxx %
b0xxxx .
b0 0
0<
b11 =
b0 >
1&
#960000
0&
#965000
1:
b1110xxxx %
b1110xxxx .
b1110 0
1;
b11 =
b11 >
1&
#970000
b0 =
11
0/
0&
b110 (
b110 *
#975000
0:
b0xxxx %
b0xxxx .
b0 0
0;
b10 =
b0 >
1&
#980000
0&
#985000
19
b1xxxx %
b1xxxx .
b1 0
1<
b10 =
b10 >
1&
#990000
b0 =
1/
0&
b111 (
b111 *
#995000
09
b0xxxx %
b0xxxx .
b0 0
0<
b0 >
1&
#1000000
0&
#1005000
1&
#1010000
b11 =
02
01
1/
0&
b1 (
b1 *
#1015000
1:
b1110xxxx %
b1110xxxx .
b1110 0
1;
b11 =
b11 >
1&
#1020000
0&
#1025000
1&
#1030000
b0 =
11
0/
0&
b10 (
b10 *
#1035000
0:
b0xxxx %
b0xxxx .
b0 0
0;
b10 =
b0 >
1&
#1040000
0&
#1045000
19
b1xxxx %
b1xxxx .
b1 0
1<
b10 =
b10 >
1&
#1050000
b0 =
1/
0&
b11 (
b11 *
#1055000
09
b0xxxx %
b0xxxx .
b0 0
0<
b1 =
b0 >
1&
#1060000
0&
#1065000
19
b1010xxxx %
b1010xxxx .
b1010 0
1;
b1 =
b1 >
1&
#1070000
b0 =
12
01
0/
0&
b100 (
b100 *
#1075000
09
b0xxxx %
b0xxxx .
b0 0
0;
b10 =
b0 >
1&
#1080000
0&
#1085000
19
b1xxxx %
b1xxxx .
b1 0
1<
b0 =
b10 >
1&
#1090000
1/
0&
b101 (
b101 *
#1095000
09
b0xxxx %
b0xxxx .
b0 0
0<
b11 =
b0 >
1&
#1100000
0&
#1105000
1:
b1110xxxx %
b1110xxxx .
b1110 0
1;
b11 =
b11 >
1&
#1110000
b0 =
11
0/
0&
b110 (
b110 *
#1115000
0:
b0xxxx %
b0xxxx .
b0 0
0;
b10 =
b0 >
1&
#1120000
0&
#1125000
19
b1xxxx %
b1xxxx .
b1 0
1<
b10 =
b10 >
1&
#1130000
b0 =
1/
0&
b111 (
b111 *
#1135000
09
b0xxxx %
b0xxxx .
b0 0
0<
b0 >
1&
#1140000
0&
#1145000
1&
#1150000
b11 =
02
01
1/
0&
b1 (
b1 *
#1155000
1:
b1110xxxx %
b1110xxxx .
b1110 0
1;
b11 =
b11 >
1&
#1160000
0&
#1165000
1&
#1170000
b0 =
11
0/
0&
b10 (
b10 *
#1175000
0:
b0xxxx %
b0xxxx .
b0 0
0;
b10 =
b0 >
1&
#1180000
0&
#1185000
19
b1xxxx %
b1xxxx .
b1 0
1<
b10 =
b10 >
1&
#1190000
b0 =
1/
0&
b11 (
b11 *
#1195000
09
b0xxxx %
b0xxxx .
b0 0
0<
b1 =
b0 >
1&
#1200000
0&
#1205000
19
b1010xxxx %
b1010xxxx .
b1010 0
1;
b1 =
b1 >
1&
#1210000
b0 =
12
01
0/
0&
b100 (
b100 *
#1215000
09
b0xxxx %
b0xxxx .
b0 0
0;
b10 =
b0 >
1&
#1220000
0&
#1225000
19
b1xxxx %
b1xxxx .
b1 0
1<
b0 =
b10 >
1&
#1230000
1/
0&
b101 (
b101 *
#1235000
09
b0xxxx %
b0xxxx .
b0 0
0<
b11 =
b0 >
1&
#1240000
0&
#1245000
1:
b1110xxxx %
b1110xxxx .
b1110 0
1;
b11 =
b11 >
1&
#1250000
b0 =
11
0/
0&
b110 (
b110 *
#1255000
0:
b0xxxx %
b0xxxx .
b0 0
0;
b10 =
b0 >
1&
#1260000
0&
#1265000
19
b1xxxx %
b1xxxx .
b1 0
1<
b10 =
b10 >
1&
#1270000
b0 =
1/
0&
b111 (
b111 *
#1275000
09
b0xxxx %
b0xxxx .
b0 0
0<
b0 >
1&
#1280000
0&
#1285000
1&
#1290000
b11 =
02
01
1/
0&
b1 (
b1 *
#1295000
1:
b1110xxxx %
b1110xxxx .
b1110 0
1;
b11 =
b11 >
1&
#1300000
0&
#1305000
1&
#1310000
b0 =
11
0/
0&
b10 (
b10 *
#1315000
0:
b0xxxx %
b0xxxx .
b0 0
0;
b10 =
b0 >
1&
#1320000
0&
#1325000
19
b1xxxx %
b1xxxx .
b1 0
1<
b10 =
b10 >
1&
#1330000
b0 =
1/
0&
b11 (
b11 *
#1335000
09
b0xxxx %
b0xxxx .
b0 0
0<
b1 =
b0 >
1&
#1340000
0&
#1345000
19
b1010xxxx %
b1010xxxx .
b1010 0
1;
b1 =
b1 >
1&
#1350000
b0 =
12
01
0/
0&
b100 (
b100 *
#1355000
09
b0xxxx %
b0xxxx .
b0 0
0;
b10 =
b0 >
1&
#1360000
0&
#1365000
19
b1xxxx %
b1xxxx .
b1 0
1<
b0 =
b10 >
1&
#1370000
1/
0&
b101 (
b101 *
#1375000
09
b0xxxx %
b0xxxx .
b0 0
0<
b11 =
b0 >
1&
#1380000
0&
#1385000
1:
b1110xxxx %
b1110xxxx .
b1110 0
1;
b11 =
b11 >
1&
#1390000
b0 =
11
0/
0&
b110 (
b110 *
#1395000
0:
b0xxxx %
b0xxxx .
b0 0
0;
b10 =
b0 >
1&
#1400000
0&
#1405000
19
b1xxxx %
b1xxxx .
b1 0
1<
b10 =
b10 >
1&
#1410000
b0 =
1/
0&
b111 (
b111 *
#1415000
09
b0xxxx %
b0xxxx .
b0 0
0<
b0 >
1&
#1420000
0&
#1425000
1&
#1430000
b1 =
02
01
0/
0&
b0 (
b0 *
